cltl/backend/__init__.py
cltl/backend/container.py
cltl/backend/server.py
cltl/backend/api/__init__.py
cltl/backend/api/backend.py
cltl/backend/api/camera.py
cltl/backend/api/gestures.py
cltl/backend/api/microphone.py
cltl/backend/api/serialization.py
cltl/backend/api/storage.py
cltl/backend/api/text_to_speech.py
cltl/backend/api/util.py
cltl/backend/impl/__init__.py
cltl/backend/impl/cached_storage.py
cltl/backend/impl/image_camera.py
cltl/backend/impl/sync_microphone.py
cltl/backend/impl/sync_tts.py
cltl/backend/source/__init__.py
cltl/backend/source/client_source.py
cltl/backend/source/console_source.py
cltl/backend/source/cv2_source.py
cltl/backend/source/pyaudio_source.py
cltl/backend/source/remote_tts.py
cltl/backend/source/webrtc_audio.py
cltl/backend/spi/__init__.py
cltl/backend/spi/audio.py
cltl/backend/spi/image.py
cltl/backend/spi/text.py
cltl.backend-0.0.dev7.data/data/VERSION/VERSION
cltl_service/backend/__init__.py
cltl_service/backend/backend.py
cltl_service/backend/schema.py
cltl_service/backend/storage.py
cltl.backend-0.0.dev7.dist-info/LICENSE
cltl.backend-0.0.dev7.dist-info/METADATA
cltl.backend-0.0.dev7.dist-info/WHEEL
cltl.backend-0.0.dev7.dist-info/entry_points.txt
cltl.backend-0.0.dev7.dist-info/top_level.txt
cltl.backend-0.0.dev7.dist-info/RECORD
