Metadata-Version: 2.1
Name: cltl.backend
Version: 0.0.dev7
Summary: Backend for Leolani
Home-page: https://github.com/leolani/cltl-backend
Author: CLTL
Author-email: t.baier@vu.nl
License: MIT License
Requires-Python: >=3.7
License-File: LICENSE
Requires-Dist: numpy
Provides-Extra: host
Requires-Dist: emissor ; extra == 'host'
Requires-Dist: cachetools ; extra == 'host'
Requires-Dist: pyaudio ; extra == 'host'
Requires-Dist: opencv-python ; extra == 'host'
Requires-Dist: flask (<2.3) ; extra == 'host'
Provides-Extra: impl
Requires-Dist: mock ; extra == 'impl'
Requires-Dist: requests ; extra == 'impl'
Requires-Dist: parameterized ; extra == 'impl'
Provides-Extra: service
Requires-Dist: cltl.combot ; extra == 'service'
Requires-Dist: emissor ; extra == 'service'
Requires-Dist: flask (<2.3) ; extra == 'service'
Requires-Dist: pyaudio ; extra == 'service'
Requires-Dist: requests ; extra == 'service'
Requires-Dist: sounddevice ; extra == 'service'
Requires-Dist: soundfile ; extra == 'service'
